srcomapi/.version
srcomapi/__init__.py
srcomapi/datatypes.py
srcomapi/exceptions.py
srcomapi/srcomapi.py
srcomapi-0.3.3.dist-info/LICENSE
srcomapi-0.3.3.dist-info/METADATA
srcomapi-0.3.3.dist-info/WHEEL
srcomapi-0.3.3.dist-info/top_level.txt
srcomapi-0.3.3.dist-info/RECORD
