Metadata-Version: 2.1
Name: srcomapi
Version: 0.3.3
Summary: A Python 3 implementation of the speedrun.com REST API
Home-page: https://github.com/blha303/srcomapi
Author: blha303
Author-email: alyssa.dev.smith+srcomapi@gmail.com
License: UNKNOWN
Project-URL: Bug tracker, https://github.com/blha303/srcomapi/issues
Platform: UNKNOWN
Classifier: Programming Language :: Python :: 3
Classifier: License :: OSI Approved :: MIT License
Classifier: Operating System :: OS Independent
Requires-Python: >=3.0
